<?xml version="1.0" encoding="utf-8" ?>
<dwsync>
<file name="10.jpg" server="orientation.ssmu.mcgill.ca/html/" local="130097407763201825" remote="130213307010000000" Dst="2" />
<file name="6.jpg" server="orientation.ssmu.mcgill.ca/html/" local="130097409146400939" remote="130213307020000000" Dst="2" />
<file name="8.jpg" server="orientation.ssmu.mcgill.ca/html/" local="130097423900954851" remote="130213307020000000" Dst="2" />
<file name="acoops.jpg" server="orientation.ssmu.mcgill.ca/html/" local="130101653356294312" remote="130213307020000000" Dst="2" />
<file name="alagoon.jpg" server="orientation.ssmu.mcgill.ca/html/" local="130101653122340930" remote="130213307020000000" Dst="2" />
<file name="background.png" server="orientation.ssmu.mcgill.ca/html/" local="129979965160000000" remote="130213307020000000" Dst="2" />
<file name="cibawoman.jpg" server="orientation.ssmu.mcgill.ca/html/" local="130101653267059208" remote="130213307020000000" Dst="2" />
<file name="cvc.png" server="orientation.ssmu.mcgill.ca/html/" local="130100552467111176" remote="130213307020000000" Dst="2" />
<file name="face-1.jpg" server="orientation.ssmu.mcgill.ca/html/" local="130090478261570037" remote="130213307020000000" Dst="2" />
<file name="face-2.jpg" server="orientation.ssmu.mcgill.ca/html/" local="130090489492832429" remote="130213307020000000" Dst="2" />
<file name="menu-active.png" server="orientation.ssmu.mcgill.ca/html/" local="130089664286119699" remote="130213307020000000" Dst="2" />
<file name="ogvidius.jpg" server="orientation.ssmu.mcgill.ca/html/" local="130101653466020588" remote="130213307020000000" Dst="2" />
<file name="subtle_surface.png" server="orientation.ssmu.mcgill.ca/html/" local="129979965160000000" remote="130213307020000000" Dst="2" />
<file name="team-1.jpg" server="orientation.ssmu.mcgill.ca/html/" local="130060092865553467" remote="130213307020000000" Dst="2" />
<file name="timeline-team.jpg" server="orientation.ssmu.mcgill.ca/html/" local="130090478890806028" remote="130213307020000000" Dst="2" />
<file name="myweek.jpg" server="orientation.ssmu.mcgill.ca/html/" local="130215066880748402" remote="130215066920000000" Dst="2" />
<file name="myweekold.jpg" server="orientation.ssmu.mcgill.ca/html/" local="130213542250000000" remote="130215239090000000" Dst="2" />
<file name="myweek-114.png" server="orientation.ssmu.mcgill.ca/html/" local="130217812749550707" remote="130218032280000000" Dst="2" />
<file name="myweek-144.png" server="orientation.ssmu.mcgill.ca/html/" local="130217812543352987" remote="130218032290000000" Dst="2" />
<file name="myweek-57.png" server="orientation.ssmu.mcgill.ca/html/" local="130217813187905053" remote="130218032290000000" Dst="2" />
<file name="myweek-72.png" server="orientation.ssmu.mcgill.ca/html/" local="130217812971939234" remote="130218032290000000" Dst="2" />
</dwsync>