<?xml version="1.0" encoding="utf-8" ?>
<dwsync>
<file name="MCSS.png" server="orientation.ssmu.mcgill.ca/html/" local="130204966500000000" remote="130204966500000000" Dst="2" />
<file name="EdFrosh.jpg" server="orientation.ssmu.mcgill.ca/html/" local="130204966480000000" remote="130204966480000000" Dst="2" />
<file name="msert.png" server="orientation.ssmu.mcgill.ca/html/" local="130215114360000000" remote="130215114360000000" Dst="2" />
<file name="athletics.jpg" server="orientation.ssmu.mcgill.ca/html/" local="130207940170000000" remote="130207940170000000" Dst="2" />
<file name="studentaid.png" server="orientation.ssmu.mcgill.ca/html/" local="130206366920000000" remote="130206366920000000" Dst="2" />
<file name="Rez.png" server="orientation.ssmu.mcgill.ca/html/" local="130204966510000000" remote="130204966510000000" Dst="2" />
<file name="ISA.png" server="orientation.ssmu.mcgill.ca/html/" local="130204966490000000" remote="130204966490000000" Dst="2" />
<file name="caps.png" server="orientation.ssmu.mcgill.ca/html/" local="130204966480000000" remote="130204966480000000" Dst="2" />
<file name="RadFrosh.jpg" server="orientation.ssmu.mcgill.ca/html/" local="130204966510000000" remote="130204966510000000" Dst="2" />
<file name="clebox.png" server="orientation.ssmu.mcgill.ca/html/" local="130209626640000000" remote="130209626640000000" Dst="2" />
<file name="MUSFrosh.png" server="orientation.ssmu.mcgill.ca/html/" local="130204966500000000" remote="130204966500000000" Dst="2" />
<file name="commamb.png" server="orientation.ssmu.mcgill.ca/html/" local="130207940180000000" remote="130207940180000000" Dst="2" />
<file name="martlet.jpg" server="orientation.ssmu.mcgill.ca/html/" local="130207940180000000" remote="130207940180000000" Dst="2" />
<file name="security.png" server="orientation.ssmu.mcgill.ca/html/" local="130204966510000000" remote="130204966510000000" Dst="2" />
<file name="ssment.jpg" server="orientation.ssmu.mcgill.ca/html/" local="130204966510000000" remote="130204966510000000" Dst="2" />
<file name="tribune.jpg" server="orientation.ssmu.mcgill.ca/html/" local="130215110760000000" remote="130215110760000000" Dst="2" />
<file name="aus.jpg" server="orientation.ssmu.mcgill.ca/html/" local="130207940170000000" remote="130207940170000000" Dst="2" />
<file name="MUSAFrosh.jpeg" server="orientation.ssmu.mcgill.ca/html/" local="130204966500000000" remote="130204966500000000" Dst="2" />
<file name="EngFrosh.png" server="orientation.ssmu.mcgill.ca/html/" local="130207940180000000" remote="130207940180000000" Dst="2" />
<file name="cake.png" server="orientation.ssmu.mcgill.ca/html/" local="130204966480000000" remote="130204966480000000" Dst="2" />
<file name="Exchange.png" server="orientation.ssmu.mcgill.ca/html/" local="130212272370000000" remote="130212272370000000" Dst="2" />
<file name="MSA.jpg" server="orientation.ssmu.mcgill.ca/html/" local="130207940190000000" remote="130207940190000000" Dst="2" />
<file name="Outdoors.jpg" server="orientation.ssmu.mcgill.ca/html/" local="130207940190000000" remote="130207940190000000" Dst="2" />
<file name="MusicFrosh.png" server="orientation.ssmu.mcgill.ca/html/" local="130207941610000000" remote="130207941610000000" Dst="2" />
<file name="rezfest.PNG" server="orientation.ssmu.mcgill.ca/html/" local="130205571690000000" remote="130205571690000000" Dst="2" />
<file name="OCFest.png" server="orientation.ssmu.mcgill.ca/html/" local="130204966500000000" remote="130204966500000000" Dst="2" />
<file name="oohlala.png" server="orientation.ssmu.mcgill.ca/html/" local="130207940190000000" remote="130207940190000000" Dst="2" />
<file name="mcgill.jpg" server="orientation.ssmu.mcgill.ca/html/" local="130207940190000000" remote="130207940190000000" Dst="2" />
<file name="healthymcg.png" server="orientation.ssmu.mcgill.ca/html/" local="130207940180000000" remote="130207940180000000" Dst="2" />
<file name="sustain.png" server="orientation.ssmu.mcgill.ca/html/" local="130204966510000000" remote="130204966510000000" Dst="2" />
<file name="Fish.jpg" server="orientation.ssmu.mcgill.ca/html/" local="130204966490000000" remote="130204966490000000" Dst="2" />
<file name="FrosherRoof.jpg" server="orientation.ssmu.mcgill.ca/html/" local="130204966490000000" remote="130204966490000000" Dst="2" />
<file name="SWSA.jpg" server="orientation.ssmu.mcgill.ca/html/" local="130207940200000000" remote="130207940200000000" Dst="2" />
<file name="ssmu.gif" server="orientation.ssmu.mcgill.ca/html/" local="130207940200000000" remote="130207940200000000" Dst="2" />
<file name="PTFrosh.png" server="orientation.ssmu.mcgill.ca/html/" local="130207940190000000" remote="130207940190000000" Dst="2" />
<file name="cle.png" server="orientation.ssmu.mcgill.ca/html/" local="130207940180000000" remote="130207940180000000" Dst="2" />
<file name="SEDE.JPG" server="orientation.ssmu.mcgill.ca/html/" local="130204966510000000" remote="130204966510000000" Dst="2" />
<file name="irsamcrop.png" server="orientation.ssmu.mcgill.ca/html/" local="130205571540000000" remote="130205571540000000" Dst="2" />
<file name="ced.jpg" server="orientation.ssmu.mcgill.ca/html/" local="130204966480000000" remote="130204966480000000" Dst="2" />
<file name="DailyDelit.gif" server="orientation.ssmu.mcgill.ca/html/" local="130204966480000000" remote="130204966480000000" Dst="2" />
<file name="DMAE.png" server="orientation.ssmu.mcgill.ca/html/" local="130207941320000000" remote="130207941320000000" Dst="2" />
<file name="mass.jpg" server="orientation.ssmu.mcgill.ca/html/" local="130207940180000000" remote="130207940180000000" Dst="2" />
<file name="cat.png" server="orientation.ssmu.mcgill.ca/html/" local="130204966480000000" remote="130204966480000000" Dst="2" />
<file name="ArtsFrosh.png" server="orientation.ssmu.mcgill.ca/html/" local="130207940170000000" remote="130207940170000000" Dst="2" />
<file name="librace.JPG" server="orientation.ssmu.mcgill.ca/html/" local="130204966490000000" remote="130204966490000000" Dst="2" />
<file name="LSAFrosh.jpg" server="orientation.ssmu.mcgill.ca/html/" local="130207941610000000" remote="130207941610000000" Dst="2" />
<file name="rezfest.png" server="orientation.ssmu.mcgill.ca/html/" local="130207940200000000" remote="130207940200000000" Dst="2" />
<file name="internationaleducation.jpg" server="orientation.ssmu.mcgill.ca/html/" local="130212271640000000" remote="130212271640000000" Dst="2" />
<file name="OutFrosh.jpg" server="orientation.ssmu.mcgill.ca/html/" local="130204966500000000" remote="130204966500000000" Dst="2" />
<file name="SUSFrosh.png" server="orientation.ssmu.mcgill.ca/html/" local="130204966510000000" remote="130204966510000000" Dst="2" />
<file name="EM.png" server="orientation.ssmu.mcgill.ca/html/" local="130207941610000000" remote="130207941610000000" Dst="2" />
<file name="DM.jpg" server="orientation.ssmu.mcgill.ca/html/" local="130207940180000000" remote="130207940180000000" Dst="2" />
<file name="mus.png" server="orientation.ssmu.mcgill.ca/html/" local="130207941610000000" remote="130207941610000000" Dst="2" />
</dwsync>